antspynet/__init__.py
antspynet/architectures/__init__.py
antspynet/architectures/create_alexnet_model.py
antspynet/architectures/create_autoencoder_model.py
antspynet/architectures/create_convolutional_autoencoder_model.py
antspynet/architectures/create_custom_model.py
antspynet/architectures/create_custom_unet_model.py
antspynet/architectures/create_cycle_gan_model.py
antspynet/architectures/create_deep_back_projection_network_model.py
antspynet/architectures/create_deep_convolutional_gan_model.py
antspynet/architectures/create_deep_denoise_super_resolution_model.py
antspynet/architectures/create_denoising_auto_encoder_super_resolution_model.py
antspynet/architectures/create_dense_model.py
antspynet/architectures/create_densenet_model.py
antspynet/architectures/create_denseunet_model.py
antspynet/architectures/create_diffusion_probabilistic_unet_model.py
antspynet/architectures/create_expanded_super_resolution_model.py
antspynet/architectures/create_image_super_resolution_model.py
antspynet/architectures/create_improved_wasserstein_gan_model.py
antspynet/architectures/create_partial_convolution_unet_model.py
antspynet/architectures/create_resnet_model.py
antspynet/architectures/create_resnet_super_resolution_model.py
antspynet/architectures/create_resunet_model.py
antspynet/architectures/create_simple_classification_with_spatial_transformer_network_model.py
antspynet/architectures/create_super_resolution_gan_model.py
antspynet/architectures/create_transformer_model.py
antspynet/architectures/create_unet_model.py
antspynet/architectures/create_vanilla_gan_model.py
antspynet/architectures/create_vgg_model.py
antspynet/architectures/create_wasserstein_gan_model.py
antspynet/architectures/create_wide_resnet_model.py
antspynet/utilities/__init__.py
antspynet/utilities/attention_utilities.py
antspynet/utilities/brain_age.py
antspynet/utilities/brain_extraction.py
antspynet/utilities/brain_mra_vessel.py
antspynet/utilities/brain_mra_vessel_segmentation.py
antspynet-0.3.1.dist-info/METADATA
antspynet-0.3.1.dist-info/WHEEL
antspynet-0.3.1.dist-info/top_level.txt
antspynet-0.3.1.dist-info/RECORD
