Metadata-Version: 2.4
Name: antspynet
Version: 0.3.1
Summary: A collection of deep learning architectures ported to the python language and tools for basic medical image processing.
Author: Brian B. Avants, Nick Cullen
Author-email: "Nicholas J. Tustison" <ntustison@gmail.com>
License: Apache License 2.0
Project-URL: homepage, https://github.com/ANTsX/ANTsPyNet
Keywords: ANTsPyNet,deep learning,medical image processing
Classifier: Programming Language :: Python :: 3
Classifier: License :: OSI Approved :: Apache Software License
Classifier: Operating System :: OS Independent
Requires-Dist: numpy
Requires-Dist: tensorflow<=2.17,>=2.11
Requires-Dist: antspyx>=0.4.2
Requires-Dist: scikit-learn
Requires-Dist: requests
Requires-Dist: statsmodels
Requires-Dist: matplotlib
